Packages/__init__.py
Packages/version.py
Packages/SingleTableQueries/SelectQueries.py
Packages/SingleTableQueries/__init__.py
tests/SingleTabselectTest.py
tests/__init__.py
Alphaworkz-0.1.dist-info/METADATA
Alphaworkz-0.1.dist-info/WHEEL
Alphaworkz-0.1.dist-info/top_level.txt
Alphaworkz-0.1.dist-info/RECORD
